zlgcan_driver_py-0.1.9.dist-info/METADATA
zlgcan_driver_py-0.1.9.dist-info/WHEEL
zlgcan_driver_py-0.1.9.dist-info/entry_points.txt
zlgcan_driver_py-0.1.9.dist-info/licenses/LICENSE.txt
zlgcan_driver_py/__init__.py
zlgcan_driver_py/zlgcan_driver_py.pypy310-pp73-x86_64-linux-gnu.so
zlgcan_driver_py-0.1.9.dist-info/RECORD
