Metadata-Version: 2.3
Name: zlgcan-driver-py
Version: 0.1.9
Classifier: Programming Language :: Rust
Classifier: Programming Language :: Python :: Implementation :: CPython
Classifier: Programming Language :: Python :: Implementation :: PyPy
Requires-Dist: python-can
License-File: LICENSE.txt
Summary: Python wrapper for zlgcan driver.
Author: Smith Jesse
License: LGPL v3
Requires-Python: >=3.8
Project-URL: homepage, https://github.com/zhuyu4839/zlgcan-driver
Project-URL: repository, https://github.com/zhuyu4839/zlgcan-driver
